MANIFEST.in
README.rst
setup.py
docs/HISTORY.txt
docs/LICENSE.GPL
docs/LICENSE.txt
ftw/__init__.py
ftw.colorbox.egg-info/PKG-INFO
ftw.colorbox.egg-info/SOURCES.txt
ftw.colorbox.egg-info/dependency_links.txt
ftw.colorbox.egg-info/entry_points.txt
ftw.colorbox.egg-info/namespace_packages.txt
ftw.colorbox.egg-info/not-zip-safe
ftw.colorbox.egg-info/requires.txt
ftw.colorbox.egg-info/top_level.txt
ftw/colorbox/__init__.py
ftw/colorbox/configure.zcml
ftw/colorbox/interfaces.py
ftw/colorbox/resources.zcml
ftw/colorbox/testing.py
ftw/colorbox/Extensions/__init__.py
ftw/colorbox/Extensions/install.py
ftw/colorbox/browser/__init__.py
ftw/colorbox/browser/colorbox_view.pt
ftw/colorbox/browser/colorbox_view.py
ftw/colorbox/browser/configure.zcml
ftw/colorbox/browser/initalize_colorbox.py
ftw/colorbox/browser/resources/border1.png
ftw/colorbox/browser/resources/border2.png
ftw/colorbox/browser/resources/borderBottomCenter.png
ftw/colorbox/browser/resources/borderBottomLeft.png
ftw/colorbox/browser/resources/borderBottomRight.png
ftw/colorbox/browser/resources/borderMiddleLeft.png
ftw/colorbox/browser/resources/borderMiddleRight.png
ftw/colorbox/browser/resources/borderTopCenter.png
ftw/colorbox/browser/resources/borderTopLeft.png
ftw/colorbox/browser/resources/borderTopRight.png
ftw/colorbox/browser/resources/colorbox.css
ftw/colorbox/browser/resources/colorbox.scss
ftw/colorbox/browser/resources/controls.png
ftw/colorbox/browser/resources/ftw-colorbox-compiled.js
ftw/colorbox/browser/resources/init-colorbox.js
ftw/colorbox/browser/resources/jquery.colorbox-min.js
ftw/colorbox/browser/resources/jquery.colorbox.js
ftw/colorbox/browser/resources/loading.gif
ftw/colorbox/browser/resources/main.js
ftw/colorbox/locales/ftw.colorbox-manual.pot
ftw/colorbox/locales/ftw.colorbox.pot
ftw/colorbox/locales/plone.pot
ftw/colorbox/locales/de/LC_MESSAGES/ftw.colorbox.po
ftw/colorbox/locales/de/LC_MESSAGES/plone.po
ftw/colorbox/locales/en/LC_MESSAGES/ftw.colorbox.po
ftw/colorbox/locales/en/LC_MESSAGES/plone.po
ftw/colorbox/locales/fr/LC_MESSAGES/ftw.colorbox.po
ftw/colorbox/locales/fr/LC_MESSAGES/plone.po
ftw/colorbox/profiles/default/browserlayer.xml
ftw/colorbox/profiles/default/cssregistry.xml
ftw/colorbox/profiles/default/jsregistry.xml
ftw/colorbox/profiles/default/metadata.xml
