Metadata-Version: 2.1
Name: ftw.colorbox
Version: 1.6.3
Summary: An image gallery for Plone using ColorBox
Home-page: https://github.com/4teamwork/ftw.colorbox
Author: 4teamwork AG
Author-email: mailto:info@4teamwork.ch
License: GPL2
Keywords: ftw colorbox
Platform: UNKNOWN
Classifier: Framework :: Plone
Classifier: Framework :: Plone :: 4.3
Classifier: Framework :: Plone :: 5.1
Classifier: Programming Language :: Python
Classifier: Topic :: Software Development :: Libraries :: Python Modules
Provides-Extra: tests
